cplusnew
