Metadata-Version: 1.0
Name: cplusnew
Version: 0.4
Summary: Convenience script for creating C++ projects with CMake setup
Home-page: UNKNOWN
Author: marksei
Author-email: mark.seidenschnur@gmail.com
License: MIT
Platform: UNKNOWN
